Metadata-Version: 2.1
Name: LongitudinalDifferenceInDifferencesPy
Version: 1.0.2
Summary: Runs a difference in differences analysis in Python.
Home-page: https://github.com/microsoft/LongitudinalDifferenceInDifferencesPy
Author: Spencer Buja
Author-email: csbuja@umich.edu
License: MIT
Platform: ALL
